stack/__init__.py
stack/exceptions.py
stack/stack.py
test/__init__.py
dsa_pack-0.0.3.dist-info/METADATA
dsa_pack-0.0.3.dist-info/WHEEL
dsa_pack-0.0.3.dist-info/top_level.txt
dsa_pack-0.0.3.dist-info/RECORD
