Metadata-Version: 2.1
Name: dsa_pack
Version: 0.0.3
Summary: A package containing essential and necessary things for Data Structures and Algorithms
Author: Bobur Yusupov
Author-email: bobur.yu06@mail.ru
Keywords: stack,queue,data structures,algorithms
Classifier: Development Status :: 3 - Alpha
Classifier: Intended Audience :: Education
Classifier: Programming Language :: Python :: 2
Classifier: Programming Language :: Python :: 3
Classifier: Operating System :: MacOS :: MacOS X
Classifier: Operating System :: Microsoft :: Windows
